{"frames":[{"filename":"enemy1_0","frame":{"x":0,"y":0,"w":50,"h":50},"rotated":false,"trimmed":false,"spriteSourceSize":{"x":0,"y":0,"w":50,"h":50},"sourceSize":{"w":50,"h":50}},{"filename":"enemy1_1","frame":{"x":50,"y":0,"w":50,"h":50},"rotated":false,"trimmed":false,"spriteSourceSize":{"x":0,"y":0,"w":50,"h":50},"sourceSize":{"w":50,"h":50}},{"filename":"enemy1_alt_0","frame":{"x":100,"y":0,"w":50,"h":50},"rotated":false,"trimmed":false,"spriteSourceSize":{"x":0,"y":0,"w":50,"h":50},"sourceSize":{"w":50,"h":50}},{"filename":"enemy1_alt_1","frame":{"x":150,"y":0,"w":50,"h":50},"rotated":false,"trimmed":false,"spriteSourceSize":{"x":0,"y":0,"w":50,"h":50},"sourceSize":{"w":50,"h":50}},{"filename":"enemy2_0","frame":{"x":0,"y":50,"w":50,"h":50},"rotated":false,"trimmed":false,"spriteSourceSize":{"x":0,"y":0,"w":50,"h":50},"sourceSize":{"w":50,"h":50}},{"filename":"enemy2_1","frame":{"x":50,"y":50,"w":50,"h":50},"rotated":false,"trimmed":false,"spriteSourceSize":{"x":0,"y":0,"w":50,"h":50},"sourceSize":{"w":50,"h":50}},{"filename":"enemy2_alt_0","frame":{"x":100,"y":50,"w":50,"h":50},"rotated":false,"trimmed":false,"spriteSourceSize":{"x":0,"y":0,"w":50,"h":50},"sourceSize":{"w":50,"h":50}},{"filename":"enemy2_alt_1","frame":{"x":150,"y":50,"w":50,"h":50},"rotated":false,"trimmed":false,"spriteSourceSize":{"x":0,"y":0,"w":50,"h":50},"sourceSize":{"w":50,"h":50}},{"filename":"enemy3_0","frame":{"x":0,"y":100,"w":50,"h":50},"rotated":false,"trimmed":false,"spriteSourceSize":{"x":0,"y":0,"w":50,"h":50},"sourceSize":{"w":50,"h":50}},{"filename":"enemy3_1","frame":{"x":50,"y":100,"w":50,"h":50},"rotated":false,"trimmed":false,"spriteSourceSize":{"x":0,"y":0,"w":50,"h":50},"sourceSize":{"w":50,"h":50}},{"filename":"enemy3_alt_0","frame":{"x":100,"y":100,"w":50,"h":50},"rotated":false,"trimmed":false,"spriteSourceSize":{"x":0,"y":0,"w":50,"h":50},"sourceSize":{"w":50,"h":50}},{"filename":"enemy3_alt_1","frame":{"x":150,"y":100,"w":50,"h":50},"rotated":false,"trimmed":false,"spriteSourceSize":{"x":0,"y":0,"w":50,"h":50},"sourceSize":{"w":50,"h":50}},{"filename":"enemy4_0","frame":{"x":0,"y":150,"w":50,"h":50},"rotated":false,"trimmed":false,"spriteSourceSize":{"x":0,"y":0,"w":50,"h":50},"sourceSize":{"w":50,"h":50}},{"filename":"enemy4_1","frame":{"x":50,"y":150,"w":50,"h":50},"rotated":false,"trimmed":false,"spriteSourceSize":{"x":0,"y":0,"w":50,"h":50},"sourceSize":{"w":50,"h":50}},{"filename":"enemy4_alt_0","frame":{"x":100,"y":150,"w":50,"h":50},"rotated":false,"trimmed":false,"spriteSourceSize":{"x":0,"y":0,"w":50,"h":50},"sourceSize":{"w":50,"h":50}},{"filename":"enemy4_alt_1","frame":{"x":150,"y":150,"w":50,"h":50},"rotated":false,"trimmed":false,"spriteSourceSize":{"x":0,"y":0,"w":50,"h":50},"sourceSize":{"w":50,"h":50}}],"meta":{"app":"https://www.leshylabs.com/apps/sstool/","version":"Leshy SpriteSheet Tool v0.8.4","image":"spritesheet.png","size":{"w":200,"h":200},"scale":1}}